aesop/__init__.py
aesop/__main__.py
aesop/app.py
aesop/commands/__init__.py
aesop/commands/aspects/__init__.py
aesop/commands/aspects/user_defined_resources/__init__.py
aesop/commands/aspects/user_defined_resources/tags/__init__.py
aesop/commands/aspects/user_defined_resources/tags/commands/__init__.py
aesop/commands/aspects/user_defined_resources/tags/commands/add.py
aesop/commands/aspects/user_defined_resources/tags/commands/assign.py
aesop/commands/aspects/user_defined_resources/tags/commands/remove.py
aesop/commands/aspects/user_defined_resources/tags/commands/unassign.py
aesop/commands/aspects/user_defined_resources/tags/models.py
aesop/commands/aspects/user_defined_resources/tags/node.py
aesop/commands/aspects/user_defined_resources/tags/tags.py
aesop/commands/common/__init__.py
aesop/commands/common/arguments.py
aesop/commands/common/entity_id.py
aesop/commands/common/enums/__init__.py
aesop/commands/common/enums/output_format.py
aesop/commands/common/exception_handler.py
aesop/commands/common/exceptions.py
aesop/commands/common/models.py
aesop/commands/common/options.py
aesop/commands/common/paginator.py
aesop/commands/documents/__init__.py
aesop/commands/documents/documents.py
aesop/commands/documents/glossaries.py
aesop/commands/documents/utils.py
aesop/commands/domains/__init__.py
aesop/commands/domains/assets.py
aesop/commands/domains/domains.py
aesop/commands/domains/saved_queries.py
aesop/commands/entities/__init__.py
aesop/commands/entities/datasets/__init__.py
aesop/commands/entities/datasets/commands/__init__.py
aesop/commands/entities/datasets/commands/get_aspect/__init__.py
aesop/commands/entities/datasets/commands/get_aspect/get_aspect.py
aesop/commands/entities/datasets/datasets.py
aesop/commands/info.py
aesop/commands/settings/__init__.py
aesop/commands/settings/custom_metadata/__init__.py
aesop/commands/settings/custom_metadata/custom_metadata.py
aesop/commands/settings/non_prod/__init__.py
aesop/commands/settings/non_prod/models.py
metaphor_aesop-0.1.9.dist-info/LICENSE
metaphor_aesop-0.1.9.dist-info/METADATA
metaphor_aesop-0.1.9.dist-info/WHEEL
metaphor_aesop-0.1.9.dist-info/entry_points.txt
metaphor_aesop-0.1.9.dist-info/RECORD
