Metadata-Version: 2.1
Name: metaphor-aesop
Version: 0.1.9
Summary: A CLI application for Metaphor metadata management and discovery
Home-page: https://metaphor.io/
License: Apache-2.0
Keywords: metadata,data catalog
Author: Metaphor
Author-email: dev@metaphor.io
Requires-Python: >=3.9,<4.0
Classifier: Development Status :: 3 - Alpha
Classifier: Intended Audience :: Developers
Classifier: License :: OSI Approved :: Apache Software License
Classifier: Programming Language :: Python :: 3
Classifier: Programming Language :: Python :: 3.9
Classifier: Programming Language :: Python :: 3.10
Classifier: Programming Language :: Python :: 3.11
Classifier: Programming Language :: Python :: 3.12
Classifier: Programming Language :: Python :: 3.13
Classifier: Topic :: Software Development
Requires-Dist: httpx (>=0.27.2,<0.28.0)
Requires-Dist: packaging (>=24.1,<25.0)
Requires-Dist: pydantic[email] (>=2.0.0,<3.0.0)
Requires-Dist: pyyaml (>=6.0.2,<7.0.0)
Requires-Dist: rich (>=13.3.5,<14.0.0)
Requires-Dist: typer (>=0.12.5,<0.13.0)
Requires-Dist: yarl (>=1.13.1,<2.0.0)
Project-URL: Documentation, https://docs.metaphor.io/
Project-URL: Repository, https://github.com/MetaphorData/aesop
